factorial_aivn_anhpv/__init__.py
factorial_aivn_anhpv/app.py
factorial_aivn_anhpv/factorial.py
factorial_aivn_anhpv-0.1.0.dist-info/METADATA
factorial_aivn_anhpv-0.1.0.dist-info/WHEEL
factorial_aivn_anhpv-0.1.0.dist-info/RECORD
